transitions_aio/__init__.py
transitions_aio/__init__.pyi
transitions_aio/core.py
transitions_aio/core.pyi
transitions_aio/py.typed
transitions_aio/experimental/__init__.py
transitions_aio/experimental/utils.py
transitions_aio/experimental/utils.pyi
transitions_aio/extensions/__init__.py
transitions_aio/extensions/__init__.pyi
transitions_aio/extensions/asyncio.py
transitions_aio/extensions/asyncio.pyi
transitions_aio/extensions/diagrams.py
transitions_aio/extensions/diagrams.pyi
transitions_aio/extensions/diagrams_base.py
transitions_aio/extensions/diagrams_base.pyi
transitions_aio/extensions/diagrams_graphviz.py
transitions_aio/extensions/diagrams_graphviz.pyi
transitions_aio/extensions/diagrams_mermaid.py
transitions_aio/extensions/diagrams_mermaid.pyi
transitions_aio/extensions/diagrams_pygraphviz.py
transitions_aio/extensions/diagrams_pygraphviz.pyi
transitions_aio/extensions/factory.py
transitions_aio/extensions/factory.pyi
transitions_aio/extensions/locking.py
transitions_aio/extensions/locking.pyi
transitions_aio/extensions/markup.py
transitions_aio/extensions/markup.pyi
transitions_aio/extensions/nesting.py
transitions_aio/extensions/nesting.pyi
transitions_aio/extensions/states.py
transitions_aio/extensions/states.pyi
transitions_aio-0.9.3.4.dist-info/licenses/LICENSE
transitions_aio-0.9.3.4.dist-info/METADATA
transitions_aio-0.9.3.4.dist-info/WHEEL
transitions_aio-0.9.3.4.dist-info/top_level.txt
transitions_aio-0.9.3.4.dist-info/RECORD
