Metadata-Version: 2.4
Name: transitions_aio
Version: 0.9.3.4
Summary: A lightweight, anyio-capable, object-oriented state machine implementation
Author-email: Tal Yarkoni <tyarkoni@gmail.com>
Maintainer-email: Matthias Urlichs <matthias@urlichs.de>
Project-URL: homepage, https://github.com/M-o-a-T/transitions_aio
Project-URL: repository, https://github.com/M-o-a-T/transitions_aio.git
Keywords: state machine
Classifier: Intended Audience :: Developers
Classifier: Programming Language :: Python :: 3
Classifier: Development Status :: 4 - Beta
Requires-Python: >=3.8
License-File: LICENSE
Provides-Extra: async
Requires-Dist: anyio; extra == "async"
Provides-Extra: dev
Requires-Dist: pytest; extra == "dev"
Requires-Dist: mock; extra == "dev"
Requires-Dist: anyio; extra == "dev"
Requires-Dist: pycodestyle; extra == "dev"
Provides-Extra: diagrams
Requires-Dist: pygraphviz; extra == "diagrams"
Provides-Extra: mypy
Requires-Dist: mypy; extra == "mypy"
Requires-Dist: graphviz; extra == "mypy"
Dynamic: license-file
